tobler/__init__.py
tobler/area_weighted/__init__.py
tobler/area_weighted/area_interpolate.py
tobler/area_weighted/area_interpolate_dask.py
tobler/area_weighted/area_join.py
tobler/dasymetric/__init__.py
tobler/dasymetric/masked_area_interpolate.py
tobler/dasymetric/raster_tools.py
tobler/model/__init__.py
tobler/model/glm.py
tobler/pycno/__init__.py
tobler/pycno/pycno.py
tobler/tests/conftest.py
tobler/tests/test_area_interpolators.py
tobler/tests/test_area_join.py
tobler/tests/test_dasymetric.py
tobler/tests/test_model.py
tobler/tests/test_pycno.py
tobler/tests/test_utils.py
tobler/util/__init__.py
tobler/util/util.py
tobler-0.13.0.dist-info/licenses/LICENSE.txt
tobler-0.13.0.dist-info/METADATA
tobler-0.13.0.dist-info/WHEEL
tobler-0.13.0.dist-info/top_level.txt
tobler-0.13.0.dist-info/RECORD
